demolab/__init__.py
demolab/app.py
demolab/config.py
demolab/network_utils.py
demolab/shell_runner.py
demolab/token_extraction.py
demolab/static/css/admin.css
demolab/static/css/lab.css
demolab/static/css/style.css
demolab/templates/admin.html
demolab/templates/demolab.html
demolab/templates/login.html
demolab-0.1.0.data/data/config/userconfig.json
demolab-0.1.0.dist-info/METADATA
demolab-0.1.0.dist-info/WHEEL
demolab-0.1.0.dist-info/entry_points.txt
demolab-0.1.0.dist-info/top_level.txt
demolab-0.1.0.dist-info/RECORD
