Metadata-Version: 2.4
Name: demolab
Version: 0.1.0
Summary: A Flask web application for URL redirection and workspace management
Home-page: https://github.com/levindemo/demolab
Author: levin
Author-email: your.email@example.com
Keywords: flask,url,redirect,workspace
Classifier: Development Status :: 3 - Alpha
Classifier: Intended Audience :: Developers
Classifier: Topic :: Internet :: WWW/HTTP :: Dynamic Content
Classifier: License :: OSI Approved :: MIT License
Classifier: Programming Language :: Python :: 3
Classifier: Programming Language :: Python :: 3.7
Classifier: Programming Language :: Python :: 3.8
Classifier: Programming Language :: Python :: 3.9
Classifier: Programming Language :: Python :: 3.10
Requires-Python: >=3.7, <4
Requires-Dist: flask>=2.0.0
Requires-Dist: requests>=2.26.0
Dynamic: author
Dynamic: author-email
Dynamic: classifier
Dynamic: description
Dynamic: description-content-type
Dynamic: home-page
Dynamic: keywords
Dynamic: requires-dist
Dynamic: requires-python
Dynamic: summary
